GenomeBaser/__init__.py
GenomeBaser/GenomeBaser
GenomeBaser/genomebaser.py
GenomeBaser-0.1.2.data/data/LICENSE
GenomeBaser-0.1.2.data/data/README.rst
GenomeBaser-0.1.2.data/data/requirements.txt
GenomeBaser-0.1.2.data/data/docs/genindex.html
GenomeBaser-0.1.2.data/data/docs/GenomeBaser.html
GenomeBaser-0.1.2.data/data/docs/index.html
GenomeBaser-0.1.2.data/data/docs/modules.html
GenomeBaser-0.1.2.data/data/docs/objects.inv
GenomeBaser-0.1.2.data/data/docs/py-modindex.html
GenomeBaser-0.1.2.data/data/docs/search.html
GenomeBaser-0.1.2.data/data/docs/searchindex.js
GenomeBaser-0.1.2.data/data/docs/_sources/GenomeBaser.txt
GenomeBaser-0.1.2.data/data/docs/_sources/index.html
GenomeBaser-0.1.2.data/data/docs/_sources/index.txt
GenomeBaser-0.1.2.data/data/docs/_sources/modules.txt
GenomeBaser-0.1.2.data/data/docs/_static/ajax-loader.gif
GenomeBaser-0.1.2.data/data/docs/_static/basic.css
GenomeBaser-0.1.2.data/data/docs/_static/comment-bright.png
GenomeBaser-0.1.2.data/data/docs/_static/comment-close.png
GenomeBaser-0.1.2.data/data/docs/_static/comment.png
GenomeBaser-0.1.2.data/data/docs/_static/default.css
GenomeBaser-0.1.2.data/data/docs/_static/doctools.js
GenomeBaser-0.1.2.data/data/docs/_static/down-pressed.png
GenomeBaser-0.1.2.data/data/docs/_static/down.png
GenomeBaser-0.1.2.data/data/docs/_static/file.png
GenomeBaser-0.1.2.data/data/docs/_static/jquery.js
GenomeBaser-0.1.2.data/data/docs/_static/minus.png
GenomeBaser-0.1.2.data/data/docs/_static/plus.png
GenomeBaser-0.1.2.data/data/docs/_static/pygments.css
GenomeBaser-0.1.2.data/data/docs/_static/searchtools.js
GenomeBaser-0.1.2.data/data/docs/_static/sidebar.js
GenomeBaser-0.1.2.data/data/docs/_static/underscore.js
GenomeBaser-0.1.2.data/data/docs/_static/up-pressed.png
GenomeBaser-0.1.2.data/data/docs/_static/up.png
GenomeBaser-0.1.2.data/data/docs/_static/websupport.js
GenomeBaser-0.1.2.data/scripts/GenomeBaser
GenomeBaser-0.1.2.dist-info/DESCRIPTION.rst
GenomeBaser-0.1.2.dist-info/METADATA
GenomeBaser-0.1.2.dist-info/metadata.json
GenomeBaser-0.1.2.dist-info/RECORD
GenomeBaser-0.1.2.dist-info/top_level.txt
GenomeBaser-0.1.2.dist-info/WHEEL
