Metadata-Version: 2.0
Name: GenomeBaser
Version: 0.1.2
Summary: GenomeBaser manages complete (bacterial) genomes from NCBI
Home-page: http://github.com/mscook/GenomeBaser
Author: Mitchell Stanton-Cook
Author-email: m.stantoncook@gmail.com
License: ECL 2.0
Platform: UNKNOWN
Classifier: Development Status :: 3 - Alpha
Classifier: Environment :: Console
Classifier: Intended Audience :: Science/Research
Classifier: License :: OSI Approved
Classifier: Natural Language :: English
Classifier: Operating System :: POSIX :: Linux
Classifier: Programming Language :: Python
Classifier: Programming Language :: Python :: 2.7
Classifier: Programming Language :: Python :: 2 :: Only
Classifier: Topic :: Scientific/Engineering :: Bio-Informatics
Requires-Dist: biopython
Requires-Dist: click
